perfcat/PerfCat.py
perfcat/__init__.py
perfcat/__main__.py
perfcat/adb/AdbWinApi.dll
perfcat/adb/AdbWinUsbApi.dll
perfcat/adb/adb.exe
perfcat/adb/fastboot.exe
perfcat/app.py
perfcat/asset.qrc
perfcat/asset_rc.py
perfcat/assets/ABOUT.md
perfcat/assets/__init__.py
perfcat/assets/css/default.css
perfcat/assets/images/logo_sws_10.png
perfcat/assets/logo.ico
perfcat/assets/svg/500px.svg
perfcat/assets/svg/IE.svg
perfcat/assets/svg/IcoMoon.svg
perfcat/assets/svg/accessibility.svg
perfcat/assets/svg/address-book.svg
perfcat/assets/svg/aid-kit.svg
perfcat/assets/svg/airplane.svg
perfcat/assets/svg/alarm.svg
perfcat/assets/svg/amazon.svg
perfcat/assets/svg/android.svg
perfcat/assets/svg/angry.svg
perfcat/assets/svg/angry2.svg
perfcat/assets/svg/appleinc.svg
perfcat/assets/svg/arrow-down-left.svg
perfcat/assets/svg/arrow-down-left2.svg
perfcat/assets/svg/arrow-down-right.svg
perfcat/assets/svg/arrow-down-right2.svg
perfcat/assets/svg/arrow-down.svg
perfcat/assets/svg/arrow-down2.svg
perfcat/assets/svg/arrow-left.svg
perfcat/assets/svg/arrow-left2.svg
perfcat/assets/svg/arrow-right.svg
perfcat/assets/svg/arrow-right2.svg
perfcat/assets/svg/arrow-up-left.svg
perfcat/assets/svg/arrow-up-left2.svg
perfcat/assets/svg/arrow-up-right.svg
perfcat/assets/svg/arrow-up-right2.svg
perfcat/assets/svg/arrow-up.svg
perfcat/assets/svg/arrow-up2.svg
perfcat/assets/svg/attachment.svg
perfcat/assets/svg/backward.svg
perfcat/assets/svg/backward2.svg
perfcat/assets/svg/baffled.svg
perfcat/assets/svg/baffled2.svg
perfcat/assets/svg/barcode.svg
perfcat/assets/svg/basecamp.svg
perfcat/assets/svg/behance.svg
perfcat/assets/svg/behance2.svg
perfcat/assets/svg/bell.svg
perfcat/assets/svg/bin.svg
perfcat/assets/svg/bin2.svg
perfcat/assets/svg/binoculars.svg
perfcat/assets/svg/blocked.svg
perfcat/assets/svg/blog.svg
perfcat/assets/svg/blogger.svg
perfcat/assets/svg/blogger2.svg
perfcat/assets/svg/bold.svg
perfcat/assets/svg/book.svg
perfcat/assets/svg/bookmark.svg
perfcat/assets/svg/bookmarks.svg
perfcat-1.0.10.dist-info/LICENSE
perfcat-1.0.10.dist-info/METADATA
perfcat-1.0.10.dist-info/WHEEL
perfcat-1.0.10.dist-info/entry_points.txt
perfcat-1.0.10.dist-info/RECORD
