Metadata-Version: 2.1
Name: perfcat
Version: 1.0.10
Summary: 基于`QT` `pyside6` 开发的安卓游戏性能采集工具。
Home-page: https://github.com/kaluluosi/PerformanceCatcher
License: MIT
Author: kaluluosi
Author-email: kaluluosi@gmail.com
Requires-Python: >=3.8,<4.0
Classifier: License :: OSI Approved :: MIT License
Classifier: Programming Language :: Python :: 3
Classifier: Programming Language :: Python :: 3.8
Classifier: Programming Language :: Python :: 3.9
Classifier: Programming Language :: Python :: 3.10
Classifier: Programming Language :: Python :: 3.11
Classifier: Programming Language :: Python :: 3.12
Requires-Dist: icespringpysidestubs-pyside6 (>=1.3.1,<2.0.0)
Requires-Dist: markdown (>=3.3.6,<4.0.0)
Requires-Dist: openpyxl (>=3.0.10,<4.0.0)
Requires-Dist: pure-python-adb (==0.3.0.dev0)
Requires-Dist: pyside6 (>=6.3.0,<7.0.0)
Requires-Dist: pyudev (>=0.23.2,<0.24.0) ; sys_platform == "linux"
Requires-Dist: pywin32 (>=303,<304) ; sys_platform == "win32"
Requires-Dist: pywin32-stubs (>=0.1.4,<0.2.0) ; sys_platform == "win32"
Requires-Dist: webob (>=1.8.7,<2.0.0)
Project-URL: Repository, https://github.com/kaluluosi/PerformanceCatcher
